LICENSE
MANIFEST.in
README.rst
setup.py
pyochre/__init__.py
pyochre.egg-info/PKG-INFO
pyochre.egg-info/SOURCES.txt
pyochre.egg-info/dependency_links.txt
pyochre.egg-info/requires.txt
pyochre.egg-info/top_level.txt
pyochre/machine_learning/__main__.py
pyochre/machine_learning/mar.py
pyochre/primary_sources/__init__.py
pyochre/primary_sources/__main__.py
pyochre/primary_sources/csv.py
pyochre/primary_sources/materials.py
pyochre/primary_sources/processor.py
pyochre/primary_sources/tei.py
pyochre/primary_sources/xml.py
pyochre/rest/__init__.py
pyochre/rest/__main__.py
pyochre/rest/connection.py
pyochre/rest/fixtures.py
pyochre/scholarly_knowledge/__main__.py
pyochre/server/__main__.py
pyochre/server/ochre/__init__.py
pyochre/server/ochre/apps.py
pyochre/server/ochre/asgi.py
pyochre/server/ochre/celery.py
pyochre/server/ochre/settings.py
pyochre/server/ochre/wsgi.py
pyochre/server/ochre/content_negotiation/__init__.py
pyochre/server/ochre/content_negotiation/ochrecontentnegotiation.py
pyochre/server/ochre/context_processors/__init__.py
pyochre/server/ochre/context_processors/app_directory.py
pyochre/server/ochre/decorators/__init__.py
pyochre/server/ochre/decorators/ochre_cache_method.py
pyochre/server/ochre/fields/__init__.py
pyochre/server/ochre/fields/actionorinterfacefield.py
pyochre/server/ochre/fields/jsoneditorfield.py
pyochre/server/ochre/fields/machinelearningmodelinteractionfield.py
pyochre/server/ochre/fields/markdowneditorfield.py
pyochre/server/ochre/fields/monacoeditorfield.py
pyochre/server/ochre/fields/objectdetectionfield.py
pyochre/server/ochre/fields/sparqleditorfield.py
pyochre/server/ochre/fields/tabularresultsfield.py
pyochre/server/ochre/fields/vegafield.py
pyochre/server/ochre/fields/vieweditfield.py
pyochre/server/ochre/fields/wikimarkdownfield.py
pyochre/server/ochre/forms/__init__.py
pyochre/server/ochre/forms/usercreateform.py
pyochre/server/ochre/migrations/0001_initial.py
pyochre/server/ochre/migrations/__init__.py
pyochre/server/ochre/models/__init__.py
pyochre/server/ochre/models/annotation.py
pyochre/server/ochre/models/asyncmixin.py
pyochre/server/ochre/models/documentation.py
