Metadata-Version: 2.1
Name: pyochre
Version: 0.0.4
Summary: Client and server for the Open Computational Humanities Research Ecosystem (OCHRE)
Home-page: https://github.com/comp-int-hum/ochre-python
Author: Tom Lippincott
Author-email: tom.lippincott@jhu.edu
Provides-Extra: ldap
Provides-Extra: postgres
Provides-Extra: torchserve
License-File: LICENSE
